wordasso/__init__.py
wordasso/phoneasso.py
wordasso/wordasso.py
wordasso-0.2.1.dist-info/METADATA
wordasso-0.2.1.dist-info/RECORD
wordasso-0.2.1.dist-info/WHEEL
wordasso-0.2.1.dist-info/top_level.txt
